cy_nutmeg-0.1.4.dist-info/licenses/LICENSE
nutmeg/nutmeg_cython.cpython-313-darwin.so
cy_nutmeg-0.1.4.dist-info/METADATA
cy_nutmeg-0.1.4.dist-info/WHEEL
cy_nutmeg-0.1.4.dist-info/top_level.txt
cy_nutmeg-0.1.4.dist-info/RECORD
